[
  {
    "idEntity": 1925902,
    "label": "Umberto Boccioni",
    "extractorType": "Person",
    "nerdType": "http://nerd.eurecom.fr/ontology#Person",
    "uri": "http://dbpedia.org/resource/Umberto_Boccioni",
    "confidence": 1.0,
    "relevance": 0.5,
    "extractor": "lupedia",
    "startChar": 1186,
    "endChar": 1202
  },
  {
    "idEntity": 1925901,
    "label": "Gabriele D'Annunzio",
    "extractorType": "Writer",
    "nerdType": "http://nerd.eurecom.fr/ontology#Person",
    "uri": "http://dbpedia.org/resource/Gabriele_d%27Annunzio",
    "confidence": 1.0,
    "relevance": 0.5,
    "extractor": "lupedia",
    "startChar": 1143,
    "endChar": 1162
  },
  {
    "idEntity": 1925899,
    "label": "Valle",
    "extractorType": "Settlement",
    "nerdType": "http://nerd.eurecom.fr/ontology#Location",
    "uri": "http://dbpedia.org/resource/Bale_%28town%29",
    "confidence": 0.891,
    "relevance": 0.5,
    "extractor": "lupedia",
    "startChar": 256,
    "endChar": 261
  },
  {
    "idEntity": 1925900,
    "label": "Casanova",
    "extractorType": "AdministrativeRegion",
    "nerdType": "http://nerd.eurecom.fr/ontology#Location",
    "uri": "http://dbpedia.org/resource/Casanova%2C_Haute-Corse",
    "confidence": 0.891,
    "relevance": 0.5,
    "extractor": "lupedia",
    "startChar": 265,
    "endChar": 273
  },
  {
    "idEntity": 1925898,
    "label": "Esso",
    "extractorType": "Company",
    "nerdType": "http://nerd.eurecom.fr/ontology#Organization",
    "uri": "http://dbpedia.org/resource/Esso",
    "confidence": 0.7546,
    "relevance": 0.5,
    "extractor": "lupedia",
    "startChar": 176,
    "endChar": 180
  }
]