[
  {
    "idEntity": 1922168,
    "label": "Emilio Salgari",
    "extractorType": "Writer",
    "nerdType": "http://nerd.eurecom.fr/ontology#Person",
    "uri": "http://dbpedia.org/resource/Emilio_Salgari",
    "confidence": 1.0,
    "relevance": 0.5,
    "extractor": "lupedia",
    "startChar": 1013,
    "endChar": 1027
  },
  {
    "idEntity": 1922166,
    "label": "Guido Gozzano",
    "extractorType": "Writer",
    "nerdType": "http://nerd.eurecom.fr/ontology#Person",
    "uri": "http://dbpedia.org/resource/Guido_Gozzano",
    "confidence": 1.0,
    "relevance": 0.5,
    "extractor": "lupedia",
    "startChar": 975,
    "endChar": 988
  },
  {
    "idEntity": 1922161,
    "label": "Barolo",
    "extractorType": "Settlement",
    "nerdType": "http://nerd.eurecom.fr/ontology#Location",
    "uri": "http://dbpedia.org/resource/Barolo_%28CN%29",
    "confidence": 0.891,
    "relevance": 0.5,
    "extractor": "lupedia",
    "startChar": 227,
    "endChar": 233
  },
  {
    "idEntity": 1922160,
    "label": "Barolo",
    "extractorType": "City",
    "nerdType": "http://nerd.eurecom.fr/ontology#Location",
    "uri": null,
    "confidence": 0.889286,
    "relevance": 0.5,
    "extractor": "alchemyapi",
    "startChar": 107,
    "endChar": 113
  },
  {
    "idEntity": 1922159,
    "label": "Museo della Scuola",
    "extractorType": "Facility",
    "nerdType": "http://nerd.eurecom.fr/ontology#Location",
    "uri": null,
    "confidence": 0.888701,
    "relevance": 0.5,
    "extractor": "alchemyapi",
    "startChar": 19,
    "endChar": 37
  },
  {
    "idEntity": 1922163,
    "label": "Novecento",
    "extractorType": "Film",
    "nerdType": "http://nerd.eurecom.fr/ontology#Product",
    "uri": "http://dbpedia.org/resource/1900_%28film%29",
    "confidence": 0.873,
    "relevance": 0.5,
    "extractor": "lupedia",
    "startChar": 689,
    "endChar": 698
  },
  {
    "idEntity": 1922162,
    "label": "Fondazione",
    "extractorType": "Book",
    "nerdType": "http://nerd.eurecom.fr/ontology#Product",
    "uri": "http://dbpedia.org/resource/Foundation_%28novel%29",
    "confidence": 0.868635,
    "relevance": 0.5,
    "extractor": "lupedia",
    "startChar": 570,
    "endChar": 580
  },
  {
    "idEntity": 1922158,
    "label": "Fondazione",
    "extractorType": "Book",
    "nerdType": "http://nerd.eurecom.fr/ontology#Product",
    "uri": "http://dbpedia.org/resource/Foundation_%28novel%29",
    "confidence": 0.868635,
    "relevance": 0.5,
    "extractor": "lupedia",
    "startChar": 3,
    "endChar": 13
  },
  {
    "idEntity": 1922164,
    "label": "Pompeo",
    "extractorType": "Person",
    "nerdType": "http://nerd.eurecom.fr/ontology#Person",
    "uri": null,
    "confidence": 0.769654,
    "relevance": 0.5,
    "extractor": "alchemyapi",
    "startChar": 775,
    "endChar": 781
  },
  {
    "idEntity": 1922169,
    "label": "Attilio Mussino",
    "extractorType": "Person",
    "nerdType": "http://nerd.eurecom.fr/ontology#Person",
    "uri": null,
    "confidence": 0.740649,
    "relevance": 0.5,
    "extractor": "alchemyapi",
    "startChar": 1056,
    "endChar": 1071
  },
  {
    "idEntity": 1922165,
    "label": "Marilena Vagliani",
    "extractorType": "Person",
    "nerdType": "http://nerd.eurecom.fr/ontology#Person",
    "uri": null,
    "confidence": 0.719004,
    "relevance": 0.5,
    "extractor": "alchemyapi",
    "startChar": 784,
    "endChar": 801
  }
]