[
  {
    "idEntity": 1921922,
    "label": "Maria Clotilde di Savoia",
    "extractorType": "BritishRoyalty",
    "nerdType": "http://nerd.eurecom.fr/ontology#Person",
    "uri": "http://dbpedia.org/resource/Princess_Maria_Clotilde_of_Savoy",
    "confidence": 1.0,
    "relevance": 0.5,
    "extractor": "lupedia",
    "startChar": 1627,
    "endChar": 1651
  },
  {
    "idEntity": 1921918,
    "label": "Restaurazione",
    "extractorType": "Country",
    "nerdType": "http://nerd.eurecom.fr/ontology#Location",
    "uri": "http://dbpedia.org/resource/Bourbon_Restoration",
    "confidence": 0.99,
    "relevance": 0.5,
    "extractor": "lupedia",
    "startChar": 1082,
    "endChar": 1095
  },
  {
    "idEntity": 1921920,
    "label": "Piemonte",
    "extractorType": "AdministrativeRegion",
    "nerdType": "http://nerd.eurecom.fr/ontology#Location",
    "uri": "http://dbpedia.org/resource/Piedmont",
    "confidence": 0.99,
    "relevance": 0.5,
    "extractor": "lupedia",
    "startChar": 1506,
    "endChar": 1514
  },
  {
    "idEntity": 1921916,
    "label": "Aosta",
    "extractorType": "Settlement",
    "nerdType": "http://nerd.eurecom.fr/ontology#Location",
    "uri": "http://dbpedia.org/resource/Aosta",
    "confidence": 0.99,
    "relevance": 0.5,
    "extractor": "lupedia",
    "startChar": 998,
    "endChar": 1003
  },
  {
    "idEntity": 1921907,
    "label": "Castellamonte",
    "extractorType": "Person",
    "nerdType": "http://nerd.eurecom.fr/ontology#Person",
    "uri": null,
    "confidence": 0.766274,
    "relevance": 0.5,
    "extractor": "alchemyapi",
    "startChar": 132,
    "endChar": 145
  },
  {
    "idEntity": 1921911,
    "label": "Castellamonte",
    "extractorType": "Person",
    "nerdType": "http://nerd.eurecom.fr/ontology#Person",
    "uri": null,
    "confidence": 0.766274,
    "relevance": 0.5,
    "extractor": "alchemyapi",
    "startChar": 540,
    "endChar": 553
  },
  {
    "idEntity": 1921921,
    "label": "Vittorio Emanuele II",
    "extractorType": "Person",
    "nerdType": "http://nerd.eurecom.fr/ontology#Person",
    "uri": null,
    "confidence": 0.632193,
    "relevance": 0.5,
    "extractor": "alchemyapi",
    "startChar": 1601,
    "endChar": 1621
  },
  {
    "idEntity": 1921919,
    "label": "Vittorio Emanuele II",
    "extractorType": "Person",
    "nerdType": "http://nerd.eurecom.fr/ontology#Person",
    "uri": null,
    "confidence": 0.632193,
    "relevance": 0.5,
    "extractor": "alchemyapi",
    "startChar": 1227,
    "endChar": 1247
  },
  {
    "idEntity": 1921908,
    "label": "Francia",
    "extractorType": "Country",
    "nerdType": "http://nerd.eurecom.fr/ontology#Location",
    "uri": null,
    "confidence": 0.60305,
    "relevance": 0.5,
    "extractor": "alchemyapi",
    "startChar": 288,
    "endChar": 295
  },
  {
    "idEntity": 1921906,
    "label": "Carlo",
    "extractorType": "Person",
    "nerdType": "http://nerd.eurecom.fr/ontology#Person",
    "uri": null,
    "confidence": 0.566069,
    "relevance": 0.5,
    "extractor": "alchemyapi",
    "startChar": 123,
    "endChar": 128
  },
  {
    "idEntity": 1921909,
    "label": "Andrea Costaguta",
    "extractorType": "Person",
    "nerdType": "http://nerd.eurecom.fr/ontology#Person",
    "uri": null,
    "confidence": 0.562421,
    "relevance": 0.5,
    "extractor": "alchemyapi",
    "startChar": 335,
    "endChar": 351
  }
]