[
  {
    "idEntity": 1935913,
    "label": "Ascanio Vitozzi",
    "extractorType": "Person",
    "nerdType": "http://nerd.eurecom.fr/ontology#Person",
    "uri": null,
    "confidence": 0.863561,
    "relevance": 0.5,
    "extractor": "alchemyapi",
    "startChar": 25,
    "endChar": 40
  },
  {
    "idEntity": 1935914,
    "label": "Dora Grossa",
    "extractorType": "Person",
    "nerdType": "http://nerd.eurecom.fr/ontology#Person",
    "uri": null,
    "confidence": 0.83955,
    "relevance": 0.5,
    "extractor": "alchemyapi",
    "startChar": 197,
    "endChar": 208
  },
  {
    "idEntity": 1935915,
    "label": "Tavigliano",
    "extractorType": "City",
    "nerdType": "http://nerd.eurecom.fr/ontology#Location",
    "uri": null,
    "confidence": 0.82536,
    "relevance": 0.5,
    "extractor": "alchemyapi",
    "startChar": 907,
    "endChar": 917
  },
  {
    "idEntity": 1935916,
    "label": "Filippo Juvarra",
    "extractorType": "Person",
    "nerdType": "http://nerd.eurecom.fr/ontology#Person",
    "uri": null,
    "confidence": 0.794047,
    "relevance": 0.5,
    "extractor": "alchemyapi",
    "startChar": 587,
    "endChar": 602
  },
  {
    "idEntity": 1935917,
    "label": "Angelo Marchini",
    "extractorType": "Person",
    "nerdType": "http://nerd.eurecom.fr/ontology#Person",
    "uri": null,
    "confidence": 0.765899,
    "relevance": 0.5,
    "extractor": "alchemyapi",
    "startChar": 385,
    "endChar": 400
  },
  {
    "idEntity": 1935918,
    "label": "Luigi Vacca",
    "extractorType": "Person",
    "nerdType": "http://nerd.eurecom.fr/ontology#Person",
    "uri": null,
    "confidence": 0.762572,
    "relevance": 0.5,
    "extractor": "alchemyapi",
    "startChar": 717,
    "endChar": 728
  },
  {
    "idEntity": 1935919,
    "label": "Castellamonte",
    "extractorType": "Person",
    "nerdType": "http://nerd.eurecom.fr/ontology#Person",
    "uri": null,
    "confidence": 0.733615,
    "relevance": 0.5,
    "extractor": "alchemyapi",
    "startChar": 782,
    "endChar": 795
  },
  {
    "idEntity": 1935920,
    "label": "Michelangelo Garove",
    "extractorType": "Person",
    "nerdType": "http://nerd.eurecom.fr/ontology#Person",
    "uri": null,
    "confidence": 0.707896,
    "relevance": 0.5,
    "extractor": "alchemyapi",
    "startChar": 798,
    "endChar": 817
  }
]