[
  {
    "idEntity": 1923879,
    "label": "Ercole Durio",
    "extractorType": "Person",
    "nerdType": "http://nerd.eurecom.fr/ontology#Person",
    "uri": null,
    "confidence": 0.33,
    "relevance": 0.5,
    "extractor": "alchemyapi",
    "startChar": 22,
    "endChar": 34
  },
  {
    "idEntity": 1923880,
    "label": "Palazzo Comunale",
    "extractorType": "Facility",
    "nerdType": "http://nerd.eurecom.fr/ontology#Location",
    "uri": null,
    "confidence": 0.33,
    "relevance": 0.5,
    "extractor": "alchemyapi",
    "startChar": 61,
    "endChar": 77
  }
]